{"cameraMode":{"drawMode":0,"name":"Shaded","section":"Shading Mode"},"sceneLighting":true,"audioPlay":false,"sceneViewState":{"m_AlwaysRefresh":false,"showFog":true,"showSkybox":true,"showFlares":true,"showImageEffects":true,"showParticleSystems":true,"showVisualEffectGraphs":true,"m_FxEnabled":true},"in2DMode":false,"pivot":{"x":-22.837778091430665,"y":23.718778610229493,"z":0.3457399010658264},"rotation":{"x":0.40303531289100649,"y":0.5566269755363464,"z":-0.35348936915397646,"w":0.6346452236175537},"size":33.36103439331055,"orthographic":false}